cloversearch/__init__.py
cloversearch/config.py
cloversearch/encoder.py
cloversearch/index_builder.py
cloversearch/indexes.py
cloversearch/processer.py
cloversearch/query.py
cloversearch/test.py
cloversearch/urls.py
cloversearch/management/__init__.py
cloversearch/management/commands/__init__.py
cloversearch/management/commands/build_index.py
cloversearch/management/commands/scan_fields.py
cloversearch/management/commands/scan_models.py
cloversearch/view/__init__.py
cloversearch/view/response.py
cloversearch/view/views.py
cloversearch-0.1.20.dist-info/LICENSE
cloversearch-0.1.20.dist-info/METADATA
cloversearch-0.1.20.dist-info/WHEEL
cloversearch-0.1.20.dist-info/top_level.txt
cloversearch-0.1.20.dist-info/RECORD
