Metadata-Version: 2.1
Name: cloversearch
Version: 0.1.20
Summary: CloverSearch搜索引擎的Django模块，使用起来超级方便！。版本[0.1.20]更新内容：优化建立索引、搜索性能，测试性能提高10倍以上，但是受限于Python语言的性能，数据量大的时候性能还是不够理想，有待进一步优化。
Home-page: https://github.com/Deali-Axy/CloverSearch
Author: DealiAxy
Author-email: dealiaxy@gmail.com
License: UNKNOWN
Platform: UNKNOWN
Classifier: Programming Language :: Python :: 3.6
Classifier: License :: OSI Approved :: GNU General Public License v3 (GPLv3)
Classifier: Operating System :: OS Independent
Requires-Dist: jieba (>=0.39)
Requires-Dist: django
Requires-Dist: ujson
